kubepi/__init__.py
kubepi/cli.py
kubepi/commands/__init__.py
kubepi/commands/cmd_apps.py
kubepi/commands/cmd_k3d.py
kubepi/commands/cmd_platform.py
kubepi/commands/cmd_preflight.py
kubepi/commands/cmd_setup.py
kubepi/helpers/__init__.py
kubepi/helpers/git.py
kubepi/helpers/k3d.py
kubepi/helpers/kube.py
kubepi-1.0.7.dist-info/AUTHORS.rst
kubepi-1.0.7.dist-info/LICENSE.txt
kubepi-1.0.7.dist-info/METADATA
kubepi-1.0.7.dist-info/WHEEL
kubepi-1.0.7.dist-info/entry_points.txt
kubepi-1.0.7.dist-info/top_level.txt
kubepi-1.0.7.dist-info/RECORD
