Metadata-Version: 2.1
Name: kubepi
Version: 1.0.7
Summary: Kubepi CLI for easier k1s setup on Raspberry PIs.
Home-page: https://github.com/nushkovg/kubepi/
Author: nushkovg
Author-email: gnuskov@protonmail.com
License: mit
Project-URL: Documentation, https://github.com/nushkovg/kubepi/
Platform: Linux
Classifier: Development Status :: 4 - Beta
Classifier: Programming Language :: Python :: 3.7
Classifier: Topic :: Utilities
Classifier: Environment :: Console
Classifier: License :: OSI Approved :: MIT License
Classifier: Operating System :: POSIX :: Linux
Requires-Python: >=3.7
Requires-Dist: click (==7.1.1)
Requires-Dist: click-log (==0.3.2)
Requires-Dist: click-spinner (==0.1.8)
Requires-Dist: docker (==4.2.0)
Requires-Dist: gitpython (==3.1.1)
Requires-Dist: paramiko (>=2.7.1)
Requires-Dist: cryptography (>=2.9.1)
Provides-Extra: testing
Requires-Dist: pytest ; extra == 'testing'
Requires-Dist: pytest-cov ; extra == 'testing'
